CHANGES
LICENSE
MANIFEST.in
README.rst
setup.py
patmat/__init__.py
patmat/match.py
patmat/mimic.py
patmat.egg-info/PKG-INFO
patmat.egg-info/SOURCES.txt
patmat.egg-info/dependency_links.txt
patmat.egg-info/top_level.txt