Metadata-Version: 1.1
Name: patmat
Version: 1.0.0
Summary: Functional-style recursive pattern matching in Python. Crazy stuff.
Home-page: https://github.com/admk/patmat
Author: Xitong Gao
Author-email: gxtfmx@gmail.com
License: The MIT License (MIT)
